eav/__init__.py
eav/admin.py
eav/decorators.py
eav/exceptions.py
eav/fields.py
eav/forms.py
eav/locale/id/LC_MESSAGES/django.po
eav/locale/ru/LC_MESSAGES/django.mo
eav/locale/ru/LC_MESSAGES/django.po
eav/locale/zh_Hans/LC_MESSAGES/django.mo
eav/locale/zh_Hans/LC_MESSAGES/django.po
eav/logic/__init__.py
eav/logic/entity_pk.py
eav/logic/managers.py
eav/logic/object_pk.py
eav/logic/slug.py
eav/managers.py
eav/migrations/0001_initial.py
eav/migrations/0002_add_entity_ct_field.py
eav/migrations/0003_auto_20210404_2209.py
eav/migrations/0004_alter_value_value_bool.py
eav/migrations/0005_auto_20210510_1305.py
eav/migrations/0006_add_entity_uuid.py
eav/migrations/0007_alter_value_value_int.py
eav/migrations/0008_use_native_slugfield.py
eav/migrations/0009_enchance_naming.py
eav/migrations/0010_dynamic_pk_type_for_models.py
eav/migrations/0011_update_defaults_and_meta.py
eav/migrations/0012_add_value_uniqueness_checks.py
eav/migrations/__init__.py
eav/models/__init__.py
eav/models/attribute.py
eav/models/entity.py
eav/models/enum_group.py
eav/models/enum_value.py
eav/models/value.py
eav/queryset.py
eav/registry.py
eav/settings.py
eav/validators.py
eav/widgets.py
django_eav2-1.8.1.dist-info/LICENSE
django_eav2-1.8.1.dist-info/METADATA
django_eav2-1.8.1.dist-info/WHEEL
django_eav2-1.8.1.dist-info/RECORD
