Metadata-Version: 2.1
Name: django-eav2
Version: 1.8.1
Summary: Entity-Attribute-Value storage for Django
Home-page: https://github.com/jazzband/django-eav2
License: GNU Lesser General Public License (LGPL), Version 3
Keywords: django,django-eav2,database,eav,sql
Author: Mauro Lizaur
Author-email: mauro@sdf.org
Requires-Python: >=3.9,<4.0
Classifier: Development Status :: 3 - Alpha
Classifier: Environment :: Web Environment
Classifier: Framework :: Django
Classifier: Framework :: Django :: 4.2
Classifier: Framework :: Django :: 5.1
Classifier: Framework :: Django :: 5.2
Classifier: Intended Audience :: Developers
Classifier: License :: OSI Approved :: GNU Library or Lesser General Public License (LGPL)
Classifier: License :: Other/Proprietary License
Classifier: Programming Language :: Python
Classifier: Programming Language :: Python :: 3
Classifier: Programming Language :: Python :: 3.9
Classifier: Programming Language :: Python :: 3.10
Classifier: Programming Language :: Python :: 3.11
Classifier: Programming Language :: Python :: 3.12
Classifier: Programming Language :: Python :: 3.13
Classifier: Topic :: Database
Classifier: Topic :: Software Development :: Libraries :: Python Modules
Requires-Dist: django (>=4.2,<5.3)
Project-URL: Repository, https://github.com/jazzband/django-eav2
